sage_language/__init__.py
sage_language/apps.py
sage_language/checks.py
sage_language/middlewares/__init__.py
sage_language/middlewares/cookie.py
sage_language/migrations/__init__.py
sage_language/templates/admin/base_site.html
sage_language/utils/__init__.py
sage_language/utils/locale.py
sage_language/views/__init__.py
sage_language/views/locale.py
django_sage_language-0.1.2.dist-info/LICENSE
django_sage_language-0.1.2.dist-info/METADATA
django_sage_language-0.1.2.dist-info/WHEEL
django_sage_language-0.1.2.dist-info/RECORD
